{
  "level": [
    {
      "id": "1",
      "x": 0,
      "z": 0,
      "dirOut": 2,
      "dirIn": "start",
      "type": "wall"
    },
    {
      "id": "9",
      "x": 1,
      "z": 0,
      "dirOut": 3,
      "dirIn": 5,
      "type": "wall"
    },
    {
      "id": "10",
      "x": 1,
      "z": 1,
      "dirOut": 1,
      "dirIn": 0,
      "type": "wall"
    },
    {
      "id": "18",
      "x": 2,
      "z": 1,
      "dirOut": 3,
      "dirIn": 4,
      "type": "wall"
    },
    {
      "id": "19",
      "x": 2,
      "z": 2,
      "dirOut": 1,
      "dirIn": 0,
      "type": "wall"
    },
    {
      "id": "26",
      "x": 3,
      "z": 1,
      "dirOut": 3,
      "dirIn": 4,
      "type": "wall"
    },
    {
      "id": "27",
      "x": 3,
      "z": 2,
      "dirOut": 1,
      "dirIn": 0,
      "type": "wall"
    },
    {
      "id": "35",
      "x": 4,
      "z": 2,
      "dirOut": 3,
      "dirIn": 4,
      "type": "wall"
    },
    {
      "id": "36",
      "x": 4,
      "z": 3,
      "dirOut": 1,
      "dirIn": 0,
      "type": "wall"
    },
    {
      "id": "43",
      "x": 5,
      "z": 2,
      "dirOut": 3,
      "dirIn": 4,
      "type": "wall"
    },
    {
      "id": "44",
      "x": 5,
      "z": 3,
      "dirOut": 1,
      "dirIn": 0,
      "type": "wall"
    },
    {
      "id": "52",
      "x": 6,
      "z": 3,
      "dirOut": 3,
      "dirIn": 4,
      "type": "wall"
    },
    {
      "id": "53",
      "x": 6,
      "z": 4,
      "dirOut": 1,
      "dirIn": 0,
      "type": "wall"
    },
    {
      "id": "60",
      "x": 7,
      "z": 3,
      "dirOut": 3,
      "dirIn": 4,
      "type": "wall"
    },
    {
      "id": "61",
      "x": 7,
      "z": 4,
      "dirOut": 1,
      "dirIn": 0,
      "type": "wall"
    }
  ],
  "size": "8"
}